Metadata-Version: 1.1
Name: lazyEdge
Version: 0.0.5
Summary: A warp on selenium.webdriver.Edge that free you from managing msedgedriver. 
Home-page: https://github.com/HellOwhatAs/lazyEdge
Author: xjq
Author-email: xjq701229@outlook.com
License: UNKNOWN
Platform: UNKNOWN
Classifier: Programming Language :: Python :: 3
